maliang/__init__.py
maliang/extensions/__init__.py
maliang/extensions/features.py
maliang/extensions/widgets.py
maliang/extensions/core/__init__.py
maliang/extensions/core/config.py
maliang/extensions/core/containers.py
maliang/extensions/utils/__init__.py
maliang/extensions/utils/functions.py
maliang/extensions/utils/windows/__init__.py
maliang/extensions/utils/windows/login.py
maliang_extensions-0.1.1.dist-info/LICENSE
maliang_extensions-0.1.1.dist-info/METADATA
maliang_extensions-0.1.1.dist-info/WHEEL
maliang_extensions-0.1.1.dist-info/top_level.txt
maliang_extensions-0.1.1.dist-info/RECORD
