Metadata-Version: 2.2
Name: maliang-extensions
Version: 0.1.1
Summary: Some extensions for maliang.
Author-email: MuXue1230 <muxuetegong@gmail.com>
Maintainer-email: MuXue1230 <muxuetegong@gmail.com>
License: MIT
Project-URL: Bug tracker, https://github.com/TempAccountOfMuxue1230/maliang-extensions/issues
Project-URL: Source code, https://github.com/TempAccountOfMuxue1230/maliang-extensions
Keywords: tkinter,gui,ui,cross-platform,themed,typed,lightweight,ui-design,modern-ui,custom,extensions
Classifier: Programming Language :: Python :: 3
Classifier: License :: OSI Approved :: MIT License
Classifier: Operating System :: Microsoft :: Windows
Classifier: Operating System :: POSIX :: Linux
Classifier: Operating System :: MacOS
Classifier: Intended Audience :: Developers
Classifier: Typing :: Typed
Requires-Python: >=3.10
License-File: LICENSE
Requires-Dist: maliang>=3.0.0rc6
Requires-Dist: typing-extensions
